odoo/addons/connector_jira/README.rst
odoo/addons/connector_jira/__init__.py
odoo/addons/connector_jira/__manifest__.py
odoo/addons/connector_jira/fields.py
odoo/addons/connector_jira/components/__init__.py
odoo/addons/connector_jira/components/common.py
odoo/addons/connector_jira/components/jira_analytic_line_batch_importer.py
odoo/addons/connector_jira/components/jira_analytic_line_importer.py
odoo/addons/connector_jira/components/jira_analytic_line_mapper.py
odoo/addons/connector_jira/components/jira_analytic_line_timestamp_batch_deleter.py
odoo/addons/connector_jira/components/jira_backend_adapter.py
odoo/addons/connector_jira/components/jira_base.py
odoo/addons/connector_jira/components/jira_base_exporter.py
odoo/addons/connector_jira/components/jira_batch_importer.py
odoo/addons/connector_jira/components/jira_binder.py
odoo/addons/connector_jira/components/jira_delayed_batch_importer.py
odoo/addons/connector_jira/components/jira_deleter.py
odoo/addons/connector_jira/components/jira_direct_batch_importer.py
odoo/addons/connector_jira/components/jira_exporter.py
odoo/addons/connector_jira/components/jira_import_mapper.py
odoo/addons/connector_jira/components/jira_importer.py
odoo/addons/connector_jira/components/jira_issue_type_adapter.py
odoo/addons/connector_jira/components/jira_issue_type_batch_importer.py
odoo/addons/connector_jira/components/jira_issue_type_mapper.py
odoo/addons/connector_jira/components/jira_mapper_from_attrs.py
odoo/addons/connector_jira/components/jira_model_binder.py
odoo/addons/connector_jira/components/jira_project_adapter.py
odoo/addons/connector_jira/components/jira_project_binder.py
odoo/addons/connector_jira/components/jira_project_project_exporter.py
odoo/addons/connector_jira/components/jira_project_project_listener.py
odoo/addons/connector_jira/components/jira_project_task_adapter.py
odoo/addons/connector_jira/components/jira_project_task_batch_importer.py
odoo/addons/connector_jira/components/jira_project_task_importer.py
odoo_addon_connector_jira-17.0.1.0.0.4.dist-info/METADATA
odoo_addon_connector_jira-17.0.1.0.0.4.dist-info/WHEEL
odoo_addon_connector_jira-17.0.1.0.0.4.dist-info/top_level.txt
odoo_addon_connector_jira-17.0.1.0.0.4.dist-info/RECORD
