Metadata-Version: 2.1
Name: odoo-addon-connector_jira
Version: 17.0.1.0.0.4
Requires-Python: >=3.10
Requires-Dist: PyJWT>=1.7.1,<2.9.0
Requires-Dist: atlassian_jwt>=3.0.0
Requires-Dist: cryptography>=38,<39
Requires-Dist: jira==3.10.5
Requires-Dist: oauthlib>=2.1.0
Requires-Dist: odoo-addon-connector>=17.0dev,<17.1dev
Requires-Dist: odoo-addon-multi_step_wizard>=17.0dev,<17.1dev
Requires-Dist: odoo-addon-queue_job>=17.0dev,<17.1dev
Requires-Dist: odoo-addon-web_widget_url_advanced>=17.0dev,<17.1dev
Requires-Dist: odoo>=17.0a,<17.1dev
Requires-Dist: requests-jwt>=0.6.0
Requires-Dist: requests-oauthlib>=1.1.0
Requires-Dist: requests-toolbelt>=0.9.1
Requires-Dist: requests>=2.21.0
Summary: JIRA Connector
Home-page: https://github.com/OCA/connector-jira
License: AGPL-3
Author: Camptocamp,Odoo Community Association (OCA)
Author-email: support@odoo-community.org
Classifier: Programming Language :: Python
Classifier: Framework :: Odoo
Classifier: Framework :: Odoo :: 17.0
Classifier: License :: OSI Approved :: GNU Affero General Public License v3
